resumake-3.1.6.dist-info/METADATA
resumake-3.1.6.dist-info/WHEEL
resumake-3.1.6.dist-info/licenses/LICENSE
resumake/__init__.py
resumake/builder/__init__.py
resumake/builder/__main__.py
resumake/components/__init__.py
resumake/components/address.py
resumake/components/author.py
resumake/components/education.py
resumake/components/experience.py
resumake/components/project.py
resumake/components/resume.py
resumake/components/skill.py
resumake/template/resume.css
resumake/template/resume.html
resumake/utils.py
resumake-3.1.6.dist-info/RECORD
