Metadata-Version: 2.1
Name: resumake
Version: 3.1.6
Summary: Generate resume using data representation objects in Python
Home-page: https://github.com/cybardev/resume
Author-Email: cybardev <sheikh@cybar.dev>
Classifier: Programming Language :: Python :: 3
Classifier: License :: OSI Approved :: GNU General Public License v3 or later (GPLv3+)
Classifier: Operating System :: OS Independent
Project-URL: Homepage, https://github.com/cybardev/resume
Project-URL: Repository, https://github.com/cybardev/resume.git
Project-URL: Documentation, https://github.com/cybardev/resume/blob/main/README.md
Requires-Python: >=3.10
